uboot/__init__.py
uboot/cli_envimg.py
uboot/cli_mkenv.py
uboot/cli_mkimg.py
uboot/common.py
uboot/env_blob.py
uboot/env_image.py
uboot/fdt_image.py
uboot/old_image.py
uboot-0.1.1.dist-info/LICENSE
uboot-0.1.1.dist-info/METADATA
uboot-0.1.1.dist-info/WHEEL
uboot-0.1.1.dist-info/entry_points.txt
uboot-0.1.1.dist-info/top_level.txt
uboot-0.1.1.dist-info/RECORD
