Metadata-Version: 2.1
Name: uboot
Version: 0.1.1
Summary: Open Source library for manipulating with U-Boot images and environment variables
Home-page: https://github.com/molejar/pyUBoot
Author: Martin Olejar
Author-email: martin.olejar@gmail.com
License: Apache 2.0
Platform: UNKNOWN
Classifier: Programming Language :: Python :: 3
Classifier: Operating System :: OS Independent
Classifier: License :: OSI Approved :: Apache Software License
Classifier: Topic :: Scientific/Engineering
Classifier: Topic :: Software Development :: Embedded Systems
Classifier: Topic :: Utilities
Requires-Python: >=3.6
Requires-Dist: click (==7.0)
Requires-Dist: easy-enum (==0.2.0)
Requires-Dist: fdt (==0.1.2)
